{"filtersResult": [0, -1, -1, -1, 0, -1, -1, -1, 0, -1, -1, -1, -1, -1, 1, 0, -1, -1, -1, 0, -1, -1, -1, -1, 0, -1, 0, -1, -1, 1, -1, -1, -1, 0, -1, 0, -1, 0, 0, 0, 0, 0]}
{"sequences": "CGTT,CTTT,CTTG"}
{"sequences": "AGTT,ATTT,ATTG"}
{"sequences": "GCTT,GTTT,GTTC"}
{"sequences": "ACTT,ATTT,ATTC"}
{"sequences": "GATT,GTTT,GTTA"}
{"sequences": "CATT,CTTT,CTTA"}
{"sequences": "CGGT,GGGT,GGCT"}
{"sequences": "CGGT,CGGG,CTGG"}
{"sequences": "AGGT,GGGT,GGAT"}
{"sequences": "AGGT,AGGG,ATGG"}
{"sequences": "CCGT,CCCT,GCCT"}
{"sequences": "AAGT,AAAT,GAAT"}
{"sequences": "GGCT,GGGT,CGGT"}
{"sequences": "GCCT,CCCT,CCGT"}
{"sequences": "GCCT,GCCC,GTCC"}
{"sequences": "ACCT,CCCT,CCAT"}
{"sequences": "ACCT,ACCC,ATCC"}
{"sequences": "AACT,AAAT,CAAT"}
{"sequences": "GGAT,GGGT,AGGT"}
{"sequences": "CCAT,CCCT,ACCT"}
{"sequences": "GAAT,AAAT,AAGT"}
{"sequences": "GAAT,GAAA,GTAA"}
{"sequences": "CAAT,AAAT,AACT"}
{"sequences": "CAAT,CAAA,CTAA"}
{"sequences": "CTTG,CTTT,CGTT"}
{"sequences": "CTTG,TTTG,TTCG"}
{"sequences": "ATTG,ATTT,AGTT"}
{"sequences": "ATTG,TTTG,TTAG"}
{"sequences": "CCTG,CCCG,TCCG"}
{"sequences": "AATG,AAAG,TAAG"}
{"sequences": "CTGG,CGGG,CGGT"}
{"sequences": "ATGG,AGGG,AGGT"}
{"sequences": "TCGG,TGGG,TGGC"}
{"sequences": "ACGG,AGGG,AGGC"}
{"sequences": "TAGG,TGGG,TGGA"}
{"sequences": "CAGG,CGGG,CGGA"}
{"sequences": "TTCG,TTTG,CTTG"}
{"sequences": "TCCG,CCCG,CCTG"}
{"sequences": "TCCG,TCCC,TGCC"}
{"sequences": "ACCG,CCCG,CCAG"}
{"sequences": "ACCG,ACCC,AGCC"}
{"sequences": "AACG,AAAG,CAAG"}
{"sequences": "TTAG,TTTG,ATTG"}
{"sequences": "CCAG,CCCG,ACCG"}
{"sequences": "TAAG,AAAG,AATG"}
{"sequences": "TAAG,TAAA,TGAA"}
{"sequences": "CAAG,AAAG,AACG"}
{"sequences": "CAAG,CAAA,CGAA"}
{"sequences": "GTTC,GTTT,GCTT"}
{"sequences": "GTTC,TTTC,TTGC"}
{"sequences": "ATTC,ATTT,ACTT"}
{"sequences": "ATTC,TTTC,TTAC"}
{"sequences": "GGTC,GGGC,TGGC"}
{"sequences": "AATC,AAAC,TAAC"}
{"sequences": "TTGC,TTTC,GTTC"}
{"sequences": "TGGC,TGGG,TCGG"}
{"sequences": "TGGC,GGGC,GGTC"}
{"sequences": "AGGC,AGGG,ACGG"}
{"sequences": "AGGC,GGGC,GGAC"}
{"sequences": "AAGC,AAAC,GAAC"}
{"sequences": "GTCC,GCCC,GCCT"}
{"sequences": "ATCC,ACCC,ACCT"}
{"sequences": "TGCC,TCCC,TCCG"}
{"sequences": "AGCC,ACCC,ACCG"}
{"sequences": "TACC,TCCC,TCCA"}
{"sequences": "GACC,GCCC,GCCA"}
{"sequences": "TTAC,TTTC,ATTC"}
{"sequences": "GGAC,GGGC,AGGC"}
{"sequences": "TAAC,AAAC,AATC"}
{"sequences": "TAAC,TAAA,TCAA"}
{"sequences": "GAAC,AAAC,AAGC"}
{"sequences": "GAAC,GAAA,GCAA"}
{"sequences": "GTTA,GTTT,GATT"}
{"sequences": "GTTA,TTTA,TTGA"}
{"sequences": "CTTA,CTTT,CATT"}
{"sequences": "CTTA,TTTA,TTCA"}
{"sequences": "GGTA,GGGA,TGGA"}
{"sequences": "CCTA,CCCA,TCCA"}
{"sequences": "TTGA,TTTA,GTTA"}
{"sequences": "TGGA,TGGG,TAGG"}
{"sequences": "TGGA,GGGA,GGTA"}
{"sequences": "CGGA,CGGG,CAGG"}
{"sequences": "CGGA,GGGA,GGCA"}
{"sequences": "CCGA,CCCA,GCCA"}
{"sequences": "TTCA,TTTA,CTTA"}
{"sequences": "GGCA,GGGA,CGGA"}
{"sequences": "TCCA,TCCC,TACC"}
{"sequences": "TCCA,CCCA,CCTA"}
{"sequences": "GCCA,GCCC,GACC"}
{"sequences": "GCCA,CCCA,CCGA"}
{"sequences": "GTAA,GAAA,GAAT"}
{"sequences": "CTAA,CAAA,CAAT"}
{"sequences": "TGAA,TAAA,TAAG"}
{"sequences": "CGAA,CAAA,CAAG"}
{"sequences": "TCAA,TAAA,TAAC"}
{"sequences": "GCAA,GAAA,GAAC"}
