{"filtersResult": [1, -1, -1, -1, 1, -1, -1, -1, 0, -1, -1, -1, -1, -1, 1, 0, -1, -1, -1, 1, -1, -1, -1, -1, 1, -1, 1, -1, -1, 1, -1, -1, -1, 0, -1, -1, -1, 0, -1, 0, 0, 0]}
{"sequences": "CGTT,TTCT,CTTG"}
{"sequences": "CGTT,CCGG,TCGT"}
{"sequences": "AGTT,TTAT,ATTG"}
{"sequences": "AGTT,AAGG,TAGT"}
{"sequences": "GCTT,TTGT,GTTC"}
{"sequences": "GCTT,GGCC,TGCT"}
{"sequences": "ACTT,TTAT,ATTC"}
{"sequences": "ACTT,AACC,TACT"}
{"sequences": "GATT,TTGT,GTTA"}
{"sequences": "GATT,GGAA,TGAT"}
{"sequences": "CATT,TTCT,CTTA"}
{"sequences": "CATT,CCAA,TCAT"}
{"sequences": "CTGT,TTGG,TGCT"}
{"sequences": "ATGT,TTGG,TGAT"}
{"sequences": "CGGT,GTGG,GGCT"}
{"sequences": "CGGT,GGCG,CTGG"}
{"sequences": "AGGT,GTGG,GGAT"}
{"sequences": "AGGT,GGAG,ATGG"}
{"sequences": "TCGT,GGTT,TGTC"}
{"sequences": "TCGT,CCGG,CGTT"}
{"sequences": "TCGT,CCGG,TTCG"}
{"sequences": "TCGT,TTCC,GTCT"}
{"sequences": "GCGT,CCGG,GTCG"}
{"sequences": "CCGT,GGTT,CGTC"}
{"sequences": "CCGT,CTCC,GCCT"}
{"sequences": "ACGT,GGTT,AGTC"}
{"sequences": "ACGT,CCGG,CGAT"}
{"sequences": "ACGT,CCGG,ATCG"}
{"sequences": "ACGT,AACC,GACT"}
{"sequences": "TAGT,GGTT,TGTA"}
{"sequences": "TAGT,AAGG,AGTT"}
{"sequences": "TAGT,AAGG,TTAG"}
{"sequences": "TAGT,TTAA,GTAT"}
{"sequences": "GAGT,AAGG,GTAG"}
{"sequences": "CAGT,GGTT,CGTA"}
{"sequences": "CAGT,AAGG,AGCT"}
{"sequences": "CAGT,AAGG,CTAG"}
{"sequences": "CAGT,CCAA,GCAT"}
{"sequences": "AAGT,GGTT,AGTA"}
{"sequences": "AAGT,ATAA,GAAT"}
{"sequences": "GTCT,TTCC,TCGT"}
{"sequences": "ATCT,TTCC,TCAT"}
{"sequences": "TGCT,CCTT,TCTG"}
{"sequences": "TGCT,TTGG,CTGT"}
{"sequences": "TGCT,GGCC,GCTT"}
{"sequences": "TGCT,GGCC,TTGC"}
{"sequences": "GGCT,CCTT,GCTG"}
{"sequences": "GGCT,GTGG,CGGT"}
{"sequences": "CGCT,GGCC,CTGC"}
{"sequences": "AGCT,CCTT,ACTG"}
{"sequences": "AGCT,AAGG,CAGT"}
{"sequences": "AGCT,GGCC,GCAT"}
{"sequences": "AGCT,GGCC,ATGC"}
{"sequences": "GCCT,CCGC,GTCC"}
{"sequences": "GCCT,CTCC,CCGT"}
{"sequences": "ACCT,CTCC,CCAT"}
{"sequences": "ACCT,CCAC,ATCC"}
{"sequences": "TACT,CCTT,TCTA"}
{"sequences": "TACT,AACC,ACTT"}
{"sequences": "TACT,AACC,TTAC"}
{"sequences": "TACT,TTAA,CTAT"}
{"sequences": "GACT,CCTT,GCTA"}
{"sequences": "GACT,AACC,ACGT"}
{"sequences": "GACT,AACC,GTAC"}
{"sequences": "GACT,GGAA,CGAT"}
{"sequences": "CACT,AACC,CTAC"}
{"sequences": "AACT,CCTT,ACTA"}
{"sequences": "AACT,ATAA,CAAT"}
{"sequences": "GTAT,TTAA,TAGT"}
{"sequences": "CTAT,TTAA,TACT"}
{"sequences": "TGAT,AATT,TATG"}
{"sequences": "TGAT,TTGG,ATGT"}
{"sequences": "TGAT,GGAA,GATT"}
{"sequences": "TGAT,GGAA,TTGA"}
{"sequences": "GGAT,AATT,GATG"}
{"sequences": "GGAT,GTGG,AGGT"}
{"sequences": "CGAT,AATT,CATG"}
{"sequences": "CGAT,CCGG,ACGT"}
{"sequences": "CGAT,GGAA,GACT"}
{"sequences": "CGAT,GGAA,CTGA"}
{"sequences": "AGAT,GGAA,ATGA"}
{"sequences": "TCAT,AATT,TATC"}
{"sequences": "TCAT,TTCC,ATCT"}
{"sequences": "TCAT,CCAA,CATT"}
{"sequences": "TCAT,CCAA,TTCA"}
{"sequences": "GCAT,AATT,GATC"}
{"sequences": "GCAT,GGCC,AGCT"}
{"sequences": "GCAT,CCAA,CAGT"}
{"sequences": "GCAT,CCAA,GTCA"}
{"sequences": "CCAT,AATT,CATC"}
{"sequences": "CCAT,CTCC,ACCT"}
{"sequences": "ACAT,CCAA,ATCA"}
{"sequences": "GAAT,AAGA,GTAA"}
{"sequences": "GAAT,ATAA,AAGT"}
{"sequences": "CAAT,AACA,CTAA"}
{"sequences": "CAAT,ATAA,AACT"}
{"sequences": "CTTG,TGTT,TTCG"}
{"sequences": "CTTG,TTCT,CGTT"}
{"sequences": "ATTG,TGTT,TTAG"}
{"sequences": "ATTG,TTAT,AGTT"}
{"sequences": "CGTG,GGTT,GTCG"}
{"sequences": "AGTG,GGTT,GTAG"}
{"sequences": "TCTG,CCTT,TGCT"}
{"sequences": "GCTG,CCTT,GGCT"}
{"sequences": "GCTG,CCTT,CTGG"}
{"sequences": "GCTG,TTGG,GTGC"}
{"sequences": "GCTG,GGCC,TGCG"}
{"sequences": "CCTG,TTGG,CTGC"}
{"sequences": "CCTG,CGCC,TCCG"}
{"sequences": "ACTG,CCTT,AGCT"}
{"sequences": "ACTG,CCTT,CTAG"}
{"sequences": "ACTG,TTGG,ATGC"}
{"sequences": "ACTG,AACC,TACG"}
{"sequences": "TATG,AATT,TGAT"}
{"sequences": "GATG,AATT,GGAT"}
{"sequences": "GATG,AATT,ATGG"}
{"sequences": "GATG,TTGG,GTGA"}
{"sequences": "GATG,GGAA,TGAG"}
{"sequences": "CATG,AATT,CGAT"}
{"sequences": "CATG,AATT,ATCG"}
{"sequences": "CATG,TTGG,CTGA"}
{"sequences": "CATG,CCAA,TCAG"}
{"sequences": "AATG,TTGG,ATGA"}
{"sequences": "AATG,AGAA,TAAG"}
{"sequences": "CTGG,CCTT,GCTG"}
{"sequences": "CTGG,GGCG,CGGT"}
{"sequences": "ATGG,AATT,GATG"}
{"sequences": "ATGG,GGAG,AGGT"}
{"sequences": "TCGG,GGTG,TGGC"}
{"sequences": "TCGG,TTCC,GTCG"}
{"sequences": "ACGG,GGAG,AGGC"}
{"sequences": "ACGG,AACC,GACG"}
{"sequences": "TAGG,GGTG,TGGA"}
{"sequences": "TAGG,TTAA,GTAG"}
{"sequences": "CAGG,GGCG,CGGA"}
{"sequences": "CAGG,CCAA,GCAG"}
{"sequences": "TTCG,TGTT,CTTG"}
{"sequences": "TTCG,CCGG,TCGT"}
{"sequences": "GTCG,GGTT,CGTG"}
{"sequences": "GTCG,CCGG,GCGT"}
{"sequences": "GTCG,TTCC,TCGG"}
{"sequences": "GTCG,TTCC,GGTC"}
{"sequences": "CTCG,TTCC,CGTC"}
{"sequences": "ATCG,AATT,CATG"}
{"sequences": "ATCG,CCGG,ACGT"}
{"sequences": "ATCG,TTCC,TCAG"}
{"sequences": "ATCG,TTCC,AGTC"}
{"sequences": "TGCG,GGCC,GCTG"}
{"sequences": "AGCG,GGCC,GCAG"}
{"sequences": "TCCG,CCTC,TGCC"}
{"sequences": "TCCG,CGCC,CCTG"}
{"sequences": "ACCG,CGCC,CCAG"}
{"sequences": "ACCG,CCAC,AGCC"}
{"sequences": "TACG,CCGG,TCGA"}
{"sequences": "TACG,AACC,ACTG"}
{"sequences": "TACG,AACC,TGAC"}
{"sequences": "TACG,TTAA,CTAG"}
{"sequences": "GACG,CCGG,GCGA"}
{"sequences": "GACG,AACC,ACGG"}
{"sequences": "GACG,AACC,GGAC"}
{"sequences": "GACG,GGAA,CGAG"}
{"sequences": "CACG,AACC,CGAC"}
{"sequences": "AACG,CCGG,ACGA"}
{"sequences": "AACG,AGAA,CAAG"}
{"sequences": "TTAG,TGTT,ATTG"}
{"sequences": "TTAG,AAGG,TAGT"}
{"sequences": "GTAG,GGTT,AGTG"}
{"sequences": "GTAG,AAGG,GAGT"}
{"sequences": "GTAG,TTAA,TAGG"}
{"sequences": "GTAG,TTAA,GGTA"}
{"sequences": "CTAG,CCTT,ACTG"}
{"sequences": "CTAG,AAGG,CAGT"}
{"sequences": "CTAG,TTAA,TACG"}
{"sequences": "CTAG,TTAA,CGTA"}
{"sequences": "ATAG,TTAA,AGTA"}
{"sequences": "TGAG,GGAA,GATG"}
{"sequences": "CGAG,GGAA,GACG"}
{"sequences": "TCAG,AAGG,TAGC"}
{"sequences": "TCAG,TTCC,ATCG"}
{"sequences": "TCAG,CCAA,CATG"}
{"sequences": "TCAG,CCAA,TGCA"}
{"sequences": "GCAG,AAGG,GAGC"}
{"sequences": "GCAG,GGCC,AGCG"}
{"sequences": "GCAG,CCAA,CAGG"}
{"sequences": "GCAG,CCAA,GGCA"}
{"sequences": "CCAG,AAGG,CAGC"}
{"sequences": "CCAG,CGCC,ACCG"}
{"sequences": "ACAG,CCAA,AGCA"}
{"sequences": "TAAG,AATA,TGAA"}
{"sequences": "TAAG,AGAA,AATG"}
{"sequences": "CAAG,AACA,CGAA"}
{"sequences": "CAAG,AGAA,AACG"}
{"sequences": "GTTC,TCTT,TTGC"}
{"sequences": "GTTC,TTGT,GCTT"}
{"sequences": "ATTC,TCTT,TTAC"}
{"sequences": "ATTC,TTAT,ACTT"}
{"sequences": "TGTC,GGTT,TCGT"}
{"sequences": "GGTC,GCGG,TGGC"}
{"sequences": "GGTC,TTCC,GTCG"}
{"sequences": "CGTC,GGTT,CCGT"}
{"sequences": "CGTC,GGTT,GTCC"}
{"sequences": "CGTC,CCGG,TCGC"}
{"sequences": "CGTC,TTCC,CTCG"}
{"sequences": "AGTC,GGTT,ACGT"}
{"sequences": "AGTC,GGTT,GTAC"}
{"sequences": "AGTC,AAGG,TAGC"}
{"sequences": "AGTC,TTCC,ATCG"}
{"sequences": "GCTC,CCTT,CTGC"}
{"sequences": "ACTC,CCTT,CTAC"}
{"sequences": "TATC,AATT,TCAT"}
{"sequences": "GATC,AATT,GCAT"}
{"sequences": "GATC,AATT,ATGC"}
{"sequences": "GATC,TTCC,GTCA"}
{"sequences": "GATC,GGAA,TGAC"}
{"sequences": "CATC,AATT,CCAT"}
{"sequences": "CATC,AATT,ATCC"}
{"sequences": "CATC,TTCC,CTCA"}
{"sequences": "CATC,CCAA,TCAC"}
{"sequences": "AATC,TTCC,ATCA"}
{"sequences": "AATC,ACAA,TAAC"}
{"sequences": "TTGC,TCTT,GTTC"}
{"sequences": "TTGC,GGCC,TGCT"}
{"sequences": "GTGC,TTGG,GCTG"}
{"sequences": "CTGC,CCTT,GCTC"}
{"sequences": "CTGC,TTGG,CCTG"}
{"sequences": "CTGC,TTGG,TGCC"}
{"sequences": "CTGC,GGCC,CGCT"}
{"sequences": "ATGC,AATT,GATC"}
{"sequences": "ATGC,TTGG,ACTG"}
{"sequences": "ATGC,TTGG,TGAC"}
{"sequences": "ATGC,GGCC,AGCT"}
{"sequences": "TGGC,GGTG,TCGG"}
{"sequences": "TGGC,GCGG,GGTC"}
{"sequences": "AGGC,GCGG,GGAC"}
{"sequences": "AGGC,GGAG,ACGG"}
{"sequences": "TCGC,CCGG,CGTC"}
{"sequences": "ACGC,CCGG,CGAC"}
{"sequences": "TAGC,AAGG,TCAG"}
{"sequences": "TAGC,AAGG,AGTC"}
{"sequences": "TAGC,GGCC,TGCA"}
{"sequences": "TAGC,TTAA,GTAC"}
{"sequences": "GAGC,AAGG,GCAG"}
{"sequences": "CAGC,AAGG,CCAG"}
{"sequences": "CAGC,AAGG,AGCC"}
{"sequences": "CAGC,GGCC,CGCA"}
{"sequences": "CAGC,CCAA,GCAC"}
{"sequences": "AAGC,GGCC,AGCA"}
{"sequences": "AAGC,ACAA,GAAC"}
{"sequences": "GTCC,GGTT,CGTC"}
{"sequences": "GTCC,CCGC,GCCT"}
{"sequences": "ATCC,AATT,CATC"}
{"sequences": "ATCC,CCAC,ACCT"}
{"sequences": "TGCC,TTGG,CTGC"}
{"sequences": "TGCC,CCTC,TCCG"}
{"sequences": "AGCC,AAGG,CAGC"}
{"sequences": "AGCC,CCAC,ACCG"}
{"sequences": "TACC,CCTC,TCCA"}
{"sequences": "TACC,TTAA,CTAC"}
{"sequences": "GACC,CCGC,GCCA"}
{"sequences": "GACC,GGAA,CGAC"}
{"sequences": "TTAC,TCTT,ATTC"}
{"sequences": "TTAC,AACC,TACT"}
{"sequences": "GTAC,GGTT,AGTC"}
{"sequences": "GTAC,AACC,GACT"}
{"sequences": "GTAC,TTAA,TAGC"}
{"sequences": "GTAC,TTAA,GCTA"}
{"sequences": "CTAC,CCTT,ACTC"}
{"sequences": "CTAC,AACC,CACT"}
{"sequences": "CTAC,TTAA,TACC"}
{"sequences": "CTAC,TTAA,CCTA"}
{"sequences": "ATAC,TTAA,ACTA"}
{"sequences": "TGAC,TTGG,ATGC"}
{"sequences": "TGAC,AACC,TACG"}
{"sequences": "TGAC,GGAA,GATC"}
{"sequences": "TGAC,GGAA,TCGA"}
{"sequences": "GGAC,GCGG,AGGC"}
{"sequences": "GGAC,AACC,GACG"}
{"sequences": "CGAC,CCGG,ACGC"}
{"sequences": "CGAC,AACC,CACG"}
{"sequences": "CGAC,GGAA,GACC"}
{"sequences": "CGAC,GGAA,CCGA"}
{"sequences": "AGAC,GGAA,ACGA"}
{"sequences": "TCAC,CCAA,CATC"}
{"sequences": "GCAC,CCAA,CAGC"}
{"sequences": "TAAC,AATA,TCAA"}
{"sequences": "TAAC,ACAA,AATC"}
{"sequences": "GAAC,AAGA,GCAA"}
{"sequences": "GAAC,ACAA,AAGC"}
{"sequences": "GTTA,TATT,TTGA"}
{"sequences": "GTTA,TTGT,GATT"}
{"sequences": "CTTA,TATT,TTCA"}
{"sequences": "CTTA,TTCT,CATT"}
{"sequences": "TGTA,GGTT,TAGT"}
{"sequences": "GGTA,GAGG,TGGA"}
{"sequences": "GGTA,TTAA,GTAG"}
{"sequences": "CGTA,GGTT,CAGT"}
{"sequences": "CGTA,GGTT,GTCA"}
{"sequences": "CGTA,CCGG,TCGA"}
{"sequences": "CGTA,TTAA,CTAG"}
{"sequences": "AGTA,GGTT,AAGT"}
{"sequences": "AGTA,GGTT,GTAA"}
{"sequences": "AGTA,AAGG,TAGA"}
{"sequences": "AGTA,TTAA,ATAG"}
{"sequences": "TCTA,CCTT,TACT"}
{"sequences": "GCTA,CCTT,GACT"}
{"sequences": "GCTA,CCTT,CTGA"}
{"sequences": "GCTA,GGCC,TGCA"}
{"sequences": "GCTA,TTAA,GTAC"}
{"sequences": "CCTA,CACC,TCCA"}
{"sequences": "CCTA,TTAA,CTAC"}
{"sequences": "ACTA,CCTT,AACT"}
{"sequences": "ACTA,CCTT,CTAA"}
{"sequences": "ACTA,AACC,TACA"}
{"sequences": "ACTA,TTAA,ATAC"}
{"sequences": "GATA,AATT,ATGA"}
{"sequences": "CATA,AATT,ATCA"}
{"sequences": "TTGA,TATT,GTTA"}
{"sequences": "TTGA,GGAA,TGAT"}
{"sequences": "GTGA,TTGG,GATG"}
{"sequences": "CTGA,CCTT,GCTA"}
{"sequences": "CTGA,TTGG,CATG"}
{"sequences": "CTGA,TTGG,TGCA"}
{"sequences": "CTGA,GGAA,CGAT"}
{"sequences": "ATGA,AATT,GATA"}
{"sequences": "ATGA,TTGG,AATG"}
{"sequences": "ATGA,TTGG,TGAA"}
{"sequences": "ATGA,GGAA,AGAT"}
{"sequences": "TGGA,GGTG,TAGG"}
{"sequences": "TGGA,GAGG,GGTA"}
{"sequences": "CGGA,GAGG,GGCA"}
{"sequences": "CGGA,GGCG,CAGG"}
{"sequences": "TCGA,CCGG,TACG"}
{"sequences": "TCGA,CCGG,CGTA"}
{"sequences": "TCGA,TTCC,GTCA"}
{"sequences": "TCGA,GGAA,TGAC"}
{"sequences": "GCGA,CCGG,GACG"}
{"sequences": "CCGA,CACC,GCCA"}
{"sequences": "CCGA,GGAA,CGAC"}
{"sequences": "ACGA,CCGG,AACG"}
{"sequences": "ACGA,CCGG,CGAA"}
{"sequences": "ACGA,AACC,GACA"}
{"sequences": "ACGA,GGAA,AGAC"}
{"sequences": "TAGA,AAGG,AGTA"}
{"sequences": "CAGA,AAGG,AGCA"}
{"sequences": "TTCA,TATT,CTTA"}
{"sequences": "TTCA,CCAA,TCAT"}
{"sequences": "GTCA,GGTT,CGTA"}
{"sequences": "GTCA,TTCC,GATC"}
{"sequences": "GTCA,TTCC,TCGA"}
{"sequences": "GTCA,CCAA,GCAT"}
{"sequences": "CTCA,TTCC,CATC"}
{"sequences": "ATCA,AATT,CATA"}
{"sequences": "ATCA,TTCC,AATC"}
{"sequences": "ATCA,TTCC,TCAA"}
{"sequences": "ATCA,CCAA,ACAT"}
{"sequences": "TGCA,TTGG,CTGA"}
{"sequences": "TGCA,GGCC,TAGC"}
{"sequences": "TGCA,GGCC,GCTA"}
{"sequences": "TGCA,CCAA,TCAG"}
{"sequences": "GGCA,GAGG,CGGA"}
{"sequences": "GGCA,CCAA,GCAG"}
{"sequences": "CGCA,GGCC,CAGC"}
{"sequences": "AGCA,AAGG,CAGA"}
{"sequences": "AGCA,GGCC,AAGC"}
{"sequences": "AGCA,GGCC,GCAA"}
{"sequences": "AGCA,CCAA,ACAG"}
{"sequences": "TCCA,CCTC,TACC"}
{"sequences": "TCCA,CACC,CCTA"}
{"sequences": "GCCA,CCGC,GACC"}
{"sequences": "GCCA,CACC,CCGA"}
{"sequences": "TACA,AACC,ACTA"}
{"sequences": "GACA,AACC,ACGA"}
{"sequences": "GTAA,GGTT,AGTA"}
{"sequences": "GTAA,AAGA,GAAT"}
{"sequences": "CTAA,CCTT,ACTA"}
{"sequences": "CTAA,AACA,CAAT"}
{"sequences": "TGAA,TTGG,ATGA"}
{"sequences": "TGAA,AATA,TAAG"}
{"sequences": "CGAA,CCGG,ACGA"}
{"sequences": "CGAA,AACA,CAAG"}
{"sequences": "TCAA,TTCC,ATCA"}
{"sequences": "TCAA,AATA,TAAC"}
{"sequences": "GCAA,GGCC,AGCA"}
{"sequences": "GCAA,AAGA,GAAC"}
