{"filtersResult": [2, -1, -1, -1, 1, -1, -1, -1, 2, -1, -1, -1, -1, -1, 2, 1, -1, -1, -1, 1, -1, -1, -1, -1, 0, -1, 0, -1, -1, 1, -1, -1, -1, 1, -1, 1, -1, 1, 1, 0, 1, 0]}
{"sequences": "TGTT,TGTC,TGCG"}
{"sequences": "TGTT,TGTA,TGAG"}
{"sequences": "TCTT,TCTG,TCGC"}
{"sequences": "TCTT,TCTA,TCAC"}
{"sequences": "TATT,TATG,TAGA"}
{"sequences": "TATT,TATC,TACA"}
{"sequences": "TTGT,CTGT,GCGT"}
{"sequences": "TTGT,ATGT,GAGT"}
{"sequences": "CTGT,ACTG,ATCG"}
{"sequences": "CTGT,CTGG,TCGG"}
{"sequences": "CTGT,CTGC,TCGC"}
{"sequences": "CTGT,CTGA,TCGA"}
{"sequences": "ATGT,CATG,CTAG"}
{"sequences": "ATGT,ATGG,TAGG"}
{"sequences": "ATGT,ATGC,TAGC"}
{"sequences": "ATGT,ATGA,TAGA"}
{"sequences": "GCGT,TCGT,TCTG"}
{"sequences": "GCGT,CCGT,CCTG"}
{"sequences": "GCGT,ACGT,ACTG"}
{"sequences": "GCGT,CGTA,CTGA"}
{"sequences": "GAGT,TAGT,TATG"}
{"sequences": "GAGT,CAGT,CATG"}
{"sequences": "GAGT,AAGT,AATG"}
{"sequences": "GAGT,AGTC,ATGC"}
{"sequences": "TTCT,GTCT,CGCT"}
{"sequences": "TTCT,ATCT,CACT"}
{"sequences": "GTCT,GTCG,TGCG"}
{"sequences": "GTCT,AGTC,ATGC"}
{"sequences": "GTCT,GTCC,TGCC"}
{"sequences": "GTCT,GTCA,TGCA"}
{"sequences": "ATCT,ATCG,TACG"}
{"sequences": "ATCT,GATC,GTAC"}
{"sequences": "ATCT,ATCC,TACC"}
{"sequences": "ATCT,ATCA,TACA"}
{"sequences": "CGCT,TGCT,TGTC"}
{"sequences": "CGCT,GGCT,GGTC"}
{"sequences": "CGCT,AGCT,AGTC"}
{"sequences": "CGCT,GCTA,GTCA"}
{"sequences": "CACT,TACT,TATC"}
{"sequences": "CACT,GACT,GATC"}
{"sequences": "CACT,AACT,AATC"}
{"sequences": "CACT,ACTG,ATCG"}
{"sequences": "TTAT,GTAT,AGAT"}
{"sequences": "TTAT,CTAT,ACAT"}
{"sequences": "GTAT,GTAG,TGAG"}
{"sequences": "GTAT,GTAC,TGAC"}
{"sequences": "GTAT,CGTA,CTGA"}
{"sequences": "GTAT,GTAA,TGAA"}
{"sequences": "CTAT,CTAG,TCAG"}
{"sequences": "CTAT,CTAC,TCAC"}
{"sequences": "CTAT,GCTA,GTCA"}
{"sequences": "CTAT,CTAA,TCAA"}
{"sequences": "AGAT,TGAT,TGTA"}
{"sequences": "AGAT,GGAT,GGTA"}
{"sequences": "AGAT,CGAT,CGTA"}
{"sequences": "AGAT,GATC,GTAC"}
{"sequences": "ACAT,TCAT,TCTA"}
{"sequences": "ACAT,GCAT,GCTA"}
{"sequences": "ACAT,CCAT,CCTA"}
{"sequences": "ACAT,CATG,CTAG"}
{"sequences": "GGTG,CGTG,TCTG"}
{"sequences": "GGTG,AGTG,TATG"}
{"sequences": "CGTG,CGTT,GCTT"}
{"sequences": "CGTG,ACGT,AGCT"}
{"sequences": "CGTG,CGTC,GCTC"}
{"sequences": "CGTG,CGTA,GCTA"}
{"sequences": "AGTG,AGTT,GATT"}
{"sequences": "AGTG,CAGT,CGAT"}
{"sequences": "AGTG,AGTC,GATC"}
{"sequences": "AGTG,AGTA,GATA"}
{"sequences": "TCTG,GCTG,GCGT"}
{"sequences": "TCTG,CCTG,CCGT"}
{"sequences": "TCTG,ACTG,ACGT"}
{"sequences": "TCTG,CTGA,CGTA"}
{"sequences": "TATG,GATG,GAGT"}
{"sequences": "TATG,CATG,CAGT"}
{"sequences": "TATG,AATG,AAGT"}
{"sequences": "TATG,ATGC,AGTC"}
{"sequences": "GTGG,GTGC,GTCT"}
{"sequences": "GTGG,GTGA,GTAT"}
{"sequences": "GCGG,GCGT,GCTC"}
{"sequences": "GCGG,GCGA,GCAC"}
{"sequences": "GAGG,GAGT,GATA"}
{"sequences": "GAGG,GAGC,GACA"}
{"sequences": "CTCG,TTCG,TTGC"}
{"sequences": "CTCG,GTCG,GTGC"}
{"sequences": "CTCG,ATCG,ATGC"}
{"sequences": "CTCG,TCGA,TGCA"}
{"sequences": "TGCG,TGCT,GTCT"}
{"sequences": "TGCG,ATGC,AGTC"}
{"sequences": "TGCG,TGCC,GTCC"}
{"sequences": "TGCG,TGCA,GTCA"}
{"sequences": "GGCG,TGCG,CTCG"}
{"sequences": "GGCG,AGCG,CACG"}
{"sequences": "AGCG,AGCT,GACT"}
{"sequences": "AGCG,TAGC,TGAC"}
{"sequences": "AGCG,AGCC,GACC"}
{"sequences": "AGCG,AGCA,GACA"}
{"sequences": "CACG,ACGT,AGCT"}
{"sequences": "CACG,TACG,TAGC"}
{"sequences": "CACG,GACG,GAGC"}
{"sequences": "CACG,AACG,AAGC"}
{"sequences": "ATAG,TTAG,TTGA"}
{"sequences": "ATAG,GTAG,GTGA"}
{"sequences": "ATAG,CTAG,CTGA"}
{"sequences": "ATAG,TAGC,TGAC"}
{"sequences": "TGAG,TGAT,GTAT"}
{"sequences": "TGAG,TGAC,GTAC"}
{"sequences": "TGAG,CTGA,CGTA"}
{"sequences": "TGAG,TGAA,GTAA"}
{"sequences": "GGAG,TGAG,ATAG"}
{"sequences": "GGAG,CGAG,ACAG"}
{"sequences": "CGAG,CGAT,GCAT"}
{"sequences": "CGAG,CGAC,GCAC"}
{"sequences": "CGAG,TCGA,TGCA"}
{"sequences": "CGAG,CGAA,GCAA"}
{"sequences": "ACAG,CAGT,CGAT"}
{"sequences": "ACAG,TCAG,TCGA"}
{"sequences": "ACAG,GCAG,GCGA"}
{"sequences": "ACAG,CCAG,CCGA"}
{"sequences": "TGTC,GGTC,GGCT"}
{"sequences": "TGTC,CGTC,CGCT"}
{"sequences": "TGTC,AGTC,AGCT"}
{"sequences": "TGTC,GTCA,GCTA"}
{"sequences": "GCTC,GCTT,CGTT"}
{"sequences": "GCTC,AGCT,ACGT"}
{"sequences": "GCTC,GCTG,CGTG"}
{"sequences": "GCTC,GCTA,CGTA"}
{"sequences": "CCTC,GCTC,TGTC"}
{"sequences": "CCTC,ACTC,TATC"}
{"sequences": "ACTC,ACTT,CATT"}
{"sequences": "ACTC,GACT,GCAT"}
{"sequences": "ACTC,ACTG,CATG"}
{"sequences": "ACTC,ACTA,CATA"}
{"sequences": "TATC,ATCG,ACTG"}
{"sequences": "TATC,GATC,GACT"}
{"sequences": "TATC,CATC,CACT"}
{"sequences": "TATC,AATC,AACT"}
{"sequences": "GTGC,TTGC,TTCG"}
{"sequences": "GTGC,CTGC,CTCG"}
{"sequences": "GTGC,ATGC,ATCG"}
{"sequences": "GTGC,TGCA,TCGA"}
{"sequences": "TCGC,TCGT,CTGT"}
{"sequences": "TCGC,TCGG,CTGG"}
{"sequences": "TCGC,ATCG,ACTG"}
{"sequences": "TCGC,TCGA,CTGA"}
{"sequences": "CCGC,TCGC,GTGC"}
{"sequences": "CCGC,ACGC,GAGC"}
{"sequences": "ACGC,ACGT,CAGT"}
{"sequences": "ACGC,ACGG,CAGG"}
{"sequences": "ACGC,TACG,TCAG"}
{"sequences": "ACGC,ACGA,CAGA"}
{"sequences": "GAGC,AGCT,ACGT"}
{"sequences": "GAGC,TAGC,TACG"}
{"sequences": "GAGC,CAGC,CACG"}
{"sequences": "GAGC,AAGC,AACG"}
{"sequences": "CTCC,CTCG,CTGT"}
{"sequences": "CTCC,CTCA,CTAT"}
{"sequences": "CGCC,CGCT,CGTG"}
{"sequences": "CGCC,CGCA,CGAG"}
{"sequences": "CACC,CACT,CATA"}
{"sequences": "CACC,CACG,CAGA"}
{"sequences": "ATAC,TACG,TCAG"}
{"sequences": "ATAC,TTAC,TTCA"}
{"sequences": "ATAC,GTAC,GTCA"}
{"sequences": "ATAC,CTAC,CTCA"}
{"sequences": "AGAC,GACT,GCAT"}
{"sequences": "AGAC,TGAC,TGCA"}
{"sequences": "AGAC,GGAC,GGCA"}
{"sequences": "AGAC,CGAC,CGCA"}
{"sequences": "TCAC,TCAT,CTAT"}
{"sequences": "TCAC,TCAG,CTAG"}
{"sequences": "TCAC,GTCA,GCTA"}
{"sequences": "TCAC,TCAA,CTAA"}
{"sequences": "GCAC,GCAT,CGAT"}
{"sequences": "GCAC,GCAG,CGAG"}
{"sequences": "GCAC,TGCA,TCGA"}
{"sequences": "GCAC,GCAA,CGAA"}
{"sequences": "CCAC,TCAC,ATAC"}
{"sequences": "CCAC,GCAC,AGAC"}
{"sequences": "TGTA,GTAC,GATC"}
{"sequences": "TGTA,GGTA,GGAT"}
{"sequences": "TGTA,CGTA,CGAT"}
{"sequences": "TGTA,AGTA,AGAT"}
{"sequences": "TCTA,CTAG,CATG"}
{"sequences": "TCTA,GCTA,GCAT"}
{"sequences": "TCTA,CCTA,CCAT"}
{"sequences": "TCTA,ACTA,ACAT"}
{"sequences": "GATA,GATT,AGTT"}
{"sequences": "GATA,CGAT,CAGT"}
{"sequences": "GATA,GATG,AGTG"}
{"sequences": "GATA,GATC,AGTC"}
{"sequences": "CATA,CATT,ACTT"}
{"sequences": "CATA,GCAT,GACT"}
{"sequences": "CATA,CATG,ACTG"}
{"sequences": "CATA,CATC,ACTC"}
{"sequences": "AATA,GATA,TGTA"}
{"sequences": "AATA,CATA,TCTA"}
{"sequences": "GTGA,TGAC,TAGC"}
{"sequences": "GTGA,TTGA,TTAG"}
{"sequences": "GTGA,CTGA,CTAG"}
{"sequences": "GTGA,ATGA,ATAG"}
{"sequences": "GCGA,CGAT,CAGT"}
{"sequences": "GCGA,TCGA,TCAG"}
{"sequences": "GCGA,CCGA,CCAG"}
{"sequences": "GCGA,ACGA,ACAG"}
{"sequences": "TAGA,TAGT,ATGT"}
{"sequences": "TAGA,TAGG,ATGG"}
{"sequences": "TAGA,CTAG,CATG"}
{"sequences": "TAGA,TAGC,ATGC"}
{"sequences": "CAGA,CAGT,ACGT"}
{"sequences": "CAGA,CAGG,ACGG"}
{"sequences": "CAGA,TCAG,TACG"}
{"sequences": "CAGA,CAGC,ACGC"}
{"sequences": "AAGA,TAGA,GTGA"}
{"sequences": "AAGA,CAGA,GCGA"}
{"sequences": "CTCA,TCAG,TACG"}
{"sequences": "CTCA,TTCA,TTAC"}
{"sequences": "CTCA,GTCA,GTAC"}
{"sequences": "CTCA,ATCA,ATAC"}
{"sequences": "CGCA,GCAT,GACT"}
{"sequences": "CGCA,TGCA,TGAC"}
{"sequences": "CGCA,GGCA,GGAC"}
{"sequences": "CGCA,AGCA,AGAC"}
{"sequences": "TACA,TACT,ATCT"}
{"sequences": "TACA,TACG,ATCG"}
{"sequences": "TACA,TACC,ATCC"}
{"sequences": "TACA,GTAC,GATC"}
{"sequences": "GACA,GACT,AGCT"}
{"sequences": "GACA,GACG,AGCG"}
{"sequences": "GACA,GACC,AGCC"}
{"sequences": "GACA,TGAC,TAGC"}
{"sequences": "AACA,TACA,CTCA"}
{"sequences": "AACA,GACA,CGCA"}
{"sequences": "ATAA,ATAG,ATGT"}
{"sequences": "ATAA,ATAC,ATCT"}
{"sequences": "AGAA,AGAT,AGTG"}
{"sequences": "AGAA,AGAC,AGCG"}
{"sequences": "ACAA,ACAT,ACTC"}
{"sequences": "ACAA,ACAG,ACGC"}
