{"filtersResult": [3, -1, -1, -1, 2, -1, -1, -1, 3, -1, -1, -1, -1, -1, 1, 1, -1, -1, -1, 2, -1, -1, -1, -1, 1, -1, 1, -1, -1, 1, -1, -1, -1, 1, -1, -1, -1, 1, -1, 0, 1, 0]}
{"sequences": "CTGT,ACCG,TATC"}
{"sequences": "ATGT,CAAG,TCTA"}
{"sequences": "GCGT,CTTA,TGAG"}
{"sequences": "GAGT,ATTC,TGCG"}
{"sequences": "GTCT,AGGC,TATG"}
{"sequences": "ATCT,GAAC,TGTA"}
{"sequences": "CGCT,GTTA,TCAC"}
{"sequences": "CACT,ATTG,TCGC"}
{"sequences": "GTAT,CGGA,TCTG"}
{"sequences": "CTAT,GCCA,TGTC"}
{"sequences": "AGAT,GTTC,TACA"}
{"sequences": "ACAT,CTTG,TAGA"}
{"sequences": "CGTG,ACCT,GAGC"}
{"sequences": "AGTG,CAAT,GCGA"}
{"sequences": "TCTG,CGGA,GTAT"}
{"sequences": "TATG,AGGC,GTCT"}
{"sequences": "CTCG,TGGA,GCAC"}
{"sequences": "TGCG,ATTC,GAGT"}
{"sequences": "AGCG,TAAC,GTGA"}
{"sequences": "CACG,AGGT,GCTC"}
{"sequences": "ATAG,TGGC,GACA"}
{"sequences": "TGAG,CTTA,GCGT"}
{"sequences": "CGAG,TCCA,GTGC"}
{"sequences": "ACAG,CGGT,GATA"}
{"sequences": "TGTC,GCCA,CTAT"}
{"sequences": "GCTC,AGGT,CACG"}
{"sequences": "ACTC,GAAT,CGCA"}
{"sequences": "TATC,ACCG,CTGT"}
{"sequences": "GTGC,TCCA,CGAG"}
{"sequences": "TCGC,ATTG,CACT"}
{"sequences": "ACGC,TAAG,CTCA"}
{"sequences": "GAGC,ACCT,CGTG"}
{"sequences": "ATAC,TCCG,CAGA"}
{"sequences": "AGAC,GCCT,CATA"}
{"sequences": "TCAC,GTTA,CGCT"}
{"sequences": "GCAC,TGGA,CTCG"}
{"sequences": "TGTA,GAAC,ATCT"}
{"sequences": "TCTA,CAAG,ATGT"}
{"sequences": "GATA,CGGT,ACAG"}
{"sequences": "CATA,GCCT,AGAC"}
{"sequences": "GTGA,TAAC,AGCG"}
{"sequences": "GCGA,CAAT,AGTG"}
{"sequences": "TAGA,CTTG,ACAT"}
{"sequences": "CAGA,TCCG,ATAC"}
{"sequences": "CTCA,TAAG,ACGC"}
{"sequences": "CGCA,GAAT,ACTC"}
{"sequences": "TACA,GTTC,AGAT"}
{"sequences": "GACA,TGGC,ATAG"}
